data_cleaner/__init__.py
data_cleaner/data_clean.py
cleanh1b-0.1.dist-info/LICENSE
cleanh1b-0.1.dist-info/METADATA
cleanh1b-0.1.dist-info/WHEEL
cleanh1b-0.1.dist-info/top_level.txt
cleanh1b-0.1.dist-info/RECORD
