Metadata-Version: 2.1
Name: cleanh1b
Version: 0.1
Summary: A package for cleaning data frames.
Home-page: https://github.com/AravindSatyan/h1b-data-cleaner
Author: Aravind Satyanarayanan
Author-email: aravind.bedean@gmail.com
Classifier: Programming Language :: Python :: 3
Classifier: License :: OSI Approved :: MIT License
Classifier: Operating System :: OS Independent
Requires-Python: >=3.6
License-File: LICENSE
Requires-Dist: pandas
